{
  "appKey": "",
  "appSecret": "",
  "encryptJs": true,
  "excludeScenes": [],
  "fb-instant-games": {},
  "includeAnySDK": false,
  "includeSDKBox": false,
  "inlineSpriteFrames": true,
  "inlineSpriteFrames_native": true,
  "jailbreakPlatform": false,
  "md5Cache": true,
  "mergeStartScene": true,
  "oauthLoginServer": "",
  "optimizeHotUpdate": false,
  "orientation": {
    "landscapeLeft": true,
    "landscapeRight": true,
    "portrait": false,
    "upsideDown": false
  },
  "packageName": "org.cocos2d.AirHockey",
  "privateKey": "",
  "qqplay": {
    "REMOTE_SERVER_ROOT": "",
    "orientation": "portrait"
  },
  "startScene": "624970ab-3f5f-4f32-ab07-bb5ad0746e3c",
  "title": "AirHockey",
  "webOrientation": "auto",
  "wechatgame": {
    "REMOTE_SERVER_ROOT": "",
    "appid": "",
    "isSubdomain": false,
    "orientation": "portrait",
    "subContext": "openDataContext"
  },
  "xxteaKey": "5f63f859-3c99-4d",
  "zipCompressJs": true
}